simple_calculator_ahmed_khaled/__init__.py
simple_calculator_ahmed_khaled/calculator.py
simple_calculator_ahmed_khaled-0.1.0.dist-info/LICENSE
simple_calculator_ahmed_khaled-0.1.0.dist-info/METADATA
simple_calculator_ahmed_khaled-0.1.0.dist-info/WHEEL
simple_calculator_ahmed_khaled-0.1.0.dist-info/top_level.txt
simple_calculator_ahmed_khaled-0.1.0.dist-info/RECORD
