Metadata-Version: 2.1
Name: simple-calculator-ahmed-khaled
Version: 0.1.0
Summary: A simple calculator package for basic math operations
Home-page: https://github.com/example/simple-calculator-ahmed-khaled
Author: Ahmed Khaled
Author-email: ahmed.khaled@example.com
License: UNKNOWN
Platform: UNKNOWN
Classifier: Programming Language :: Python :: 3
Classifier: License :: OSI Approved :: MIT License
Classifier: Operating System :: OS Independent
Requires-Python: >=3.6
License-File: LICENSE
